beobench/__init__.py
beobench/cli.py
beobench/constants.py
beobench/logging.py
beobench/utils.py
beobench/beobench_contrib/gyms/boptest/Dockerfile
beobench/beobench_contrib/gyms/boptest/README.rst
beobench/beobench_contrib/gyms/boptest/env_creator.py
beobench/beobench_contrib/gyms/boptest/installer.py
beobench/beobench_contrib/gyms/energym/Dockerfile
beobench/beobench_contrib/gyms/energym/README.rst
beobench/beobench_contrib/gyms/energym/energymGymEnv.py
beobench/beobench_contrib/gyms/energym/env_creator.py
beobench/beobench_contrib/gyms/sinergym/Dockerfile
beobench/beobench_contrib/gyms/sinergym/LICENSE
beobench/beobench_contrib/gyms/sinergym/README.rst
beobench/beobench_contrib/gyms/sinergym/env_creator.py
beobench/beobench_contrib/gyms/sinergym_minimal/Dockerfile
beobench/beobench_contrib/gyms/sinergym_minimal/env_creator.py
beobench/beobench_contrib/gyms/sinergym_minimal/test.yml
beobench/data/__init__.py
beobench/data/agents/__init__.py
beobench/data/agents/energym_controller.py
beobench/data/agents/random_action.py
beobench/data/agents/rllib.py
beobench/data/agents/sweep.py
beobench/data/configs/__init__.py
beobench/data/configs/default.yaml
beobench/data/configs/demo.yaml
beobench/data/configs/energym_controller.yaml
beobench/data/configs/energym_wrapper.yaml
beobench/data/configs/gym_boptest.yaml
beobench/data/configs/gym_energym.yaml
beobench/data/configs/gym_sinergym.yaml
beobench/data/configs/method_ppo.yaml
beobench/data/configs/method_random_action.yaml
beobench/data/configs/test_energym.yaml
beobench/data/configs/archive/rewex01.yaml
beobench/data/configs/archive/rewex01_grid.yaml
beobench/data/configs/archive/rewex01_grid02.yaml
beobench/data/configs/archive/rewex02.yaml
beobench/data/configs/baselines/boptest_arroyo2022_dqn.yaml
beobench/data/configs/baselines/boptest_arroyo2022_random_agent.yaml
beobench/data/configs/baselines/sinergym_figure4_dqn.yaml
beobench/data/configs/baselines/sinergym_figure4_random_agent.yaml
beobench-0.5.4.dist-info/AUTHORS.rst
beobench-0.5.4.dist-info/LICENSE
beobench-0.5.4.dist-info/METADATA
beobench-0.5.4.dist-info/WHEEL
beobench-0.5.4.dist-info/entry_points.txt
beobench-0.5.4.dist-info/top_level.txt
beobench-0.5.4.dist-info/RECORD
