Metadata-Version: 2.1
Name: beobench
Version: 0.5.4
Summary: Beobench is a toolkit providing easy and unified access to building control environments for reinforcement learning (RL).
Author: Beobench authors
License: MIT license
Project-URL: Documentation, https://beobench.readthedocs.io/
Project-URL: Code, https://github.com/rdnfn/beobench
Project-URL: Issue tracker, https://github.com/rdnfn/beobench/issues
Keywords: beobench
Classifier: Development Status :: 3 - Alpha
Classifier: Intended Audience :: Developers
Classifier: License :: OSI Approved :: MIT License
Classifier: Natural Language :: English
Classifier: Programming Language :: Python :: 3
Classifier: Programming Language :: Python :: 3.6
Classifier: Programming Language :: Python :: 3.7
Classifier: Programming Language :: Python :: 3.8
Classifier: Programming Language :: Python :: 3.9
Requires-Python: >=3.6
License-File: LICENSE
License-File: AUTHORS.rst
Requires-Dist: docker
Requires-Dist: click
Requires-Dist: pyyaml
Requires-Dist: importlib-resources
Requires-Dist: loguru
Provides-Extra: extended
Requires-Dist: gym ; extra == 'extended'
Requires-Dist: wandb ; extra == 'extended'
Provides-Extra: rllib
Requires-Dist: ray[rllib] (<=2.1.0) ; extra == 'rllib'
Requires-Dist: numpy (<1.24.0) ; extra == 'rllib'
Requires-Dist: torch ; extra == 'rllib'
Requires-Dist: gym ; extra == 'rllib'
Requires-Dist: wandb ; extra == 'rllib'
